counselor/client.py
counselor/discovery.py
counselor/filter.py
counselor/kv_updater.py
counselor/kv_watcher.py
counselor/service_watcher.py
counselor/signal.py
counselor/trigger.py
counselor/watcher.py
counselor/endpoint/check_endpoint.py
counselor/endpoint/common.py
counselor/endpoint/decoder.py
counselor/endpoint/encoder.py
counselor/endpoint/entity.py
counselor/endpoint/http_client.py
counselor/endpoint/http_endpoint.py
counselor/endpoint/kv_endpoint.py
counselor/endpoint/service_endpoint.py
counselor-0.3.2.dist-info/LICENSE.txt
counselor-0.3.2.dist-info/METADATA
counselor-0.3.2.dist-info/WHEEL
counselor-0.3.2.dist-info/top_level.txt
counselor-0.3.2.dist-info/RECORD
