Metadata-Version: 2.1
Name: counselor
Version: 0.3.2
Summary: Package to interact with HashiCorp Consul
Home-page: https://github.com/joergeschmann/counselor
Author: Joerg Eschmann
Author-email: joerg.eschmann@gmail.com
License: MIT
Keywords: consul
Platform: UNKNOWN
Classifier: Development Status :: 3 - Alpha
Classifier: Intended Audience :: Developers
Classifier: Topic :: Software Development :: Build Tools
Classifier: License :: OSI Approved :: MIT License
Classifier: Programming Language :: Python :: 3.6
Requires-Dist: requests (>=2.22.0)
